snowdrop/bin/x13as
snowdrop/bin/x13as.exe
snowdrop/bin/x13as.tar
snowdrop/src/__init__.py
snowdrop/src/abm/cbdc.py
snowdrop/src/abm/three_instruments.py
snowdrop/src/abm/two_instruments.py
snowdrop/src/climate/DICE/__init__.py
snowdrop/src/climate/DICE/dice.py
snowdrop/src/driver.py
snowdrop/src/driver.spec
snowdrop/src/epidemic/__init__.py
snowdrop/src/epidemic/covid19.py
snowdrop/src/epidemic/data.py
snowdrop/src/epidemic/ert.py
snowdrop/src/epidemic/gsw.py
snowdrop/src/epidemic/gsw_tunes.py
snowdrop/src/epidemic/gsw_v2.py
snowdrop/src/epidemic/sir_params.py
snowdrop/src/graphs/__init__.py
snowdrop/src/graphs/animation.py
snowdrop/src/graphs/util.py
snowdrop/src/gui/__init__.py
snowdrop/src/gui/clientGui.py
snowdrop/src/gui/dialog.py
snowdrop/src/gui/multiColumnListBox.py
snowdrop/src/gui/mytable.py
snowdrop/src/gui/scrollableTable.py
snowdrop/src/gui/table.py
snowdrop/src/gui/temp.py
snowdrop/src/info/__init__.py
snowdrop/src/info/graph.py
snowdrop/src/info/graphs.py
snowdrop/src/info/test.py
snowdrop/src/info.py
snowdrop/src/misc/__init__.py
snowdrop/src/misc/display.py
snowdrop/src/misc/info.py
snowdrop/src/misc/latex.py
snowdrop/src/misc/linter.py
snowdrop/src/misc/termcolor.py
snowdrop/src/misc/text2latex.py
snowdrop/src/model/__init__.py
snowdrop/src/model/factory.py
snowdrop/src/model/interface.py
snowdrop/src/model/model.py
snowdrop/src/model/settings.py
snowdrop/src/model/util.py
snowdrop/src/numeric/__init__.py
snowdrop/src/numeric/bayes/__init__.py
snowdrop/src/numeric/bayes/mcmc.py
snowdrop/src/numeric/dp/__init__.py
snowdrop/src/numeric/dp/bellman.py
snowdrop/src/numeric/dp/collard.py
snowdrop/src/numeric/dp/discrete.py
snowdrop/src/numeric/dp/grids.py
snowdrop/src/numeric/dp/hjb.py
snowdrop/src/numeric/dp/olg.py
snowdrop/src/numeric/dp/tauchen.py
snowdrop/src/numeric/dp/test.py
snowdrop/src/numeric/dp/util.py
snowdrop/src/numeric/estimation/__init__.py
snowdrop/src/numeric/estimation/estimate.py
snowdrop/src/numeric/estimation/test_grad.py
pysnowdrop-1.0.10.dist-info/entry_points.txt
pysnowdrop-1.0.10.dist-info/licenses/LICENSE
pysnowdrop-1.0.10.dist-info/METADATA
pysnowdrop-1.0.10.dist-info/WHEEL
pysnowdrop-1.0.10.dist-info/RECORD
