Metadata-Version: 2.4
Name: pysnowdrop
Version: 1.0.10
Summary: Python Platform for DSGE Modeling
License: LGPL-3.0-or-later
License-File: LICENSE
Keywords: DSGE,Macroeconomic Modeling
Author: Alexei Goumilevski
Author-email: agoumilevski@hotmail.com
Maintainer: Alexei Goumilevski
Maintainer-email: Agoumilevski@hotmail.com
Requires-Python: >=3.10,<4.0
Classifier: Environment :: Console
Classifier: Intended Audience :: Science/Research
Classifier: License :: OSI Approved :: GNU Lesser General Public License v3 or later (LGPLv3+)
Classifier: Natural Language :: English
Classifier: Operating System :: OS Independent
Classifier: Programming Language :: Python
Classifier: Programming Language :: Python :: 3
Classifier: Programming Language :: Python :: 3.10
Classifier: Programming Language :: Python :: 3.11
Classifier: Programming Language :: Python :: 3.12
Classifier: Programming Language :: Python :: 3.13
Classifier: Programming Language :: Python :: 3.14
Classifier: Topic :: Software Development
Provides-Extra: autograd
Provides-Extra: compecon
Provides-Extra: glob2
Provides-Extra: pdflatex
Provides-Extra: pykalman
Provides-Extra: pylatex
Provides-Extra: quantecon
Provides-Extra: reportlab
Provides-Extra: scikit-learn
Provides-Extra: textwrap3
Requires-Dist: PyLaTeX (>=1.4.2,<2.0.0) ; extra == "pylatex"
Requires-Dist: PyPDF2 (>=3.0.1,<4.0.0)
Requires-Dist: PyYAML (>=6.0.1,<7.0.0)
Requires-Dist: autograd (>=1.7.0,<2.0.0) ; extra == "autograd"
Requires-Dist: compecon (>=2024.5.19,<2025.0.0) ; extra == "compecon"
Requires-Dist: corner (>=2.2.2,<3.0.0)
Requires-Dist: dill (>=0.3.8,<0.4.0)
Requires-Dist: emcee (>=3.1.6,<4.0.0)
Requires-Dist: filterpy (>=1.4.5,<2.0.0)
Requires-Dist: glob2 (>=0.7,<0.8) ; extra == "glob2"
Requires-Dist: graphviz (>=0.20.3,<0.21.0)
Requires-Dist: lark (>=1.2.2,<2.0.0)
Requires-Dist: matplotlib (==3.10.0)
Requires-Dist: networkx (>=3.2,<4.0)
Requires-Dist: numba (>=0.59.0,<0.60.0)
Requires-Dist: numpy (==1.26.4)
Requires-Dist: pandas (>=2.1.4,<3.0.0)
Requires-Dist: particles (>=0.4,<0.5)
Requires-Dist: pdfkit (>=1.0.0,<2.0.0)
Requires-Dist: pdflatex (>=0.1.3,<0.2.0) ; extra == "pdflatex"
Requires-Dist: pydot (>=2.0.0,<3.0.0)
Requires-Dist: pykalman (>=0.9.7,<0.10.0) ; extra == "pykalman"
Requires-Dist: pylatex (>=1.4.2,<2.0.0) ; extra == "pylatex"
Requires-Dist: pymcmcstat (>=1.9.1,<2.0.0)
Requires-Dist: pytest (>=7.4.0,<8.0.0)
Requires-Dist: quantecon (>=0.7.2,<0.8.0) ; extra == "quantecon"
Requires-Dist: reportlab (>=4.2.2,<5.0.0) ; extra == "reportlab"
Requires-Dist: ruamel.yaml (==0.17.21)
Requires-Dist: scipy (==1.11.4)
Requires-Dist: seaborn (>=0.13.0,<0.14.0)
Requires-Dist: statsmodels (>=0.14.0,<0.15.0)
Requires-Dist: symengine (>=0.11.0,<0.12.0)
Requires-Dist: sympy (>=1.12,<2.0)
Requires-Dist: textwrap3 (>=0.9.2,<0.10.0) ; extra == "textwrap3"
Requires-Dist: xlsxwriter (>=3.2.0,<4.0.0)
Project-URL: Repository, https://github.com/gumilevskij/Framework.git
